MANIFEST.in
README.rst
setup.py
content_links/__init__.py
content_links/models.py
content_links/test_settings.py
content_links/views.py
content_links.egg-info/PKG-INFO
content_links.egg-info/SOURCES.txt
content_links.egg-info/dependency_links.txt
content_links.egg-info/not-zip-safe
content_links.egg-info/top_level.txt
content_links/templates/admin/content/content_links/default.html
content_links/templates/admin/content/content_links/init.html
content_links/templates/content/content_links/default.html
content_links/tests/__init__.py
content_links/tests/models.py
content_links/tests/tests.py