Metadata-Version: 1.0
Name: content-links
Version: 0.1.2
Summary: UNKNOWN
Home-page: https://github.com/incuna/content-links/
Author: Incuna Ltd
Author-email: admin@incuna.com
License: UNKNOWN
Platform: UNKNOWN
